{
"meta":{"test_sets":[],"test_metrics":[],"learn_metrics":[{"best_value":"Min","name":"Logloss"}],"launch_mode":"Train","parameters":"","iteration_count":200,"learn_sets":["learn"],"name":"experiment"},
"iterations":[
{"learn":[0.5793310953],"iteration":0,"passed_time":0.007042679621,"remaining_time":1.401493245},
{"learn":[0.4782390293],"iteration":1,"passed_time":0.01369631415,"remaining_time":1.355935101},
{"learn":[0.3935329923],"iteration":2,"passed_time":0.02007475889,"remaining_time":1.318242501},
{"learn":[0.3362448157],"iteration":3,"passed_time":0.02679072878,"remaining_time":1.31274571},
{"learn":[0.2851085621],"iteration":4,"passed_time":0.03353134937,"remaining_time":1.307722626},
{"learn":[0.2452762742],"iteration":5,"passed_time":0.03993552837,"remaining_time":1.291248751},
{"learn":[0.2040483314],"iteration":6,"passed_time":0.0464997097,"remaining_time":1.282063425},
{"learn":[0.1797476549],"iteration":7,"passed_time":0.05299666246,"remaining_time":1.271919899},
{"learn":[0.1535667734],"iteration":8,"passed_time":0.06011665648,"remaining_time":1.275809043},
{"learn":[0.1321300137],"iteration":9,"passed_time":0.06645384489,"remaining_time":1.262623053},
{"learn":[0.1144652248],"iteration":10,"passed_time":0.07290369342,"remaining_time":1.252618005},
{"learn":[0.09941713359],"iteration":11,"passed_time":0.07919715992,"remaining_time":1.240755505},
{"learn":[0.08705304458],"iteration":12,"passed_time":0.08540538732,"remaining_time":1.228523648},
{"learn":[0.07822597863],"iteration":13,"passed_time":0.09145164595,"remaining_time":1.215000439},
{"learn":[0.07213475258],"iteration":14,"passed_time":0.09784823855,"remaining_time":1.206794942},
{"learn":[0.06521936272],"iteration":15,"passed_time":0.1042940539,"remaining_time":1.19938162},
{"learn":[0.05974626997],"iteration":16,"passed_time":0.1103292162,"remaining_time":1.187661562},
{"learn":[0.05568261555],"iteration":17,"passed_time":0.1164773844,"remaining_time":1.177715776},
{"learn":[0.05194878251],"iteration":18,"passed_time":0.1226285171,"remaining_time":1.168197978},
{"learn":[0.04848008684],"iteration":19,"passed_time":0.1285645335,"remaining_time":1.157080801},
{"learn":[0.04517656085],"iteration":20,"passed_time":0.1352985522,"remaining_time":1.153259087},
{"learn":[0.04357139029],"iteration":21,"passed_time":0.1416029745,"remaining_time":1.145696794},
{"learn":[0.04114055865],"iteration":22,"passed_time":0.1482112305,"remaining_time":1.140582078},
{"learn":[0.03959893927],"iteration":23,"passed_time":0.1545015968,"remaining_time":1.13301171},
{"learn":[0.03782451154],"iteration":24,"passed_time":0.1606568106,"remaining_time":1.124597675},
{"learn":[0.03658429409],"iteration":25,"passed_time":0.1668565716,"remaining_time":1.116655517},
{"learn":[0.03552978712],"iteration":26,"passed_time":0.1729009914,"remaining_time":1.107847093},
{"learn":[0.03464424037],"iteration":27,"passed_time":0.1787509557,"remaining_time":1.098041585},
{"learn":[0.03401691707],"iteration":28,"passed_time":0.18436572,"remaining_time":1.087122004},
{"learn":[0.03265683591],"iteration":29,"passed_time":0.1904678515,"remaining_time":1.079317825},
{"learn":[0.03159012051],"iteration":30,"passed_time":0.1962342222,"remaining_time":1.069793018},
{"learn":[0.03124049428],"iteration":31,"passed_time":0.2024251113,"remaining_time":1.062731834},
{"learn":[0.03067953651],"iteration":32,"passed_time":0.2090999264,"remaining_time":1.058172355},
{"learn":[0.0301912325],"iteration":33,"passed_time":0.2152631681,"remaining_time":1.050990762},
{"learn":[0.02986059256],"iteration":34,"passed_time":0.2215408011,"remaining_time":1.044406634},
{"learn":[0.02961351325],"iteration":35,"passed_time":0.2279211935,"remaining_time":1.038307659},
{"learn":[0.0291949781],"iteration":36,"passed_time":0.2340411506,"remaining_time":1.03104615},
{"learn":[0.02844922029],"iteration":37,"passed_time":0.2401515578,"remaining_time":1.023804009},
{"learn":[0.02764932221],"iteration":38,"passed_time":0.2463075541,"remaining_time":1.016808108},
{"learn":[0.02746757287],"iteration":39,"passed_time":0.2527003571,"remaining_time":1.010801429},
{"learn":[0.02730966128],"iteration":40,"passed_time":0.258609494,"remaining_time":1.002900233},
{"learn":[0.02643631547],"iteration":41,"passed_time":0.2647389648,"remaining_time":0.9959227722},
{"learn":[0.02581094406],"iteration":42,"passed_time":0.2715019887,"remaining_time":0.9912979588},
{"learn":[0.02510596588],"iteration":43,"passed_time":0.2778631469,"remaining_time":0.985151157},
{"learn":[0.02425002551],"iteration":44,"passed_time":0.2841176458,"remaining_time":0.9786274465},
{"learn":[0.02381206957],"iteration":45,"passed_time":0.2905536678,"remaining_time":0.9727231486},
{"learn":[0.02369682145],"iteration":46,"passed_time":0.2963601397,"remaining_time":0.9647468378},
{"learn":[0.02327824611],"iteration":47,"passed_time":0.3025095646,"remaining_time":0.9579469545},
{"learn":[0.02300719969],"iteration":48,"passed_time":0.3085031906,"remaining_time":0.9506935056},
{"learn":[0.02271570186],"iteration":49,"passed_time":0.3148760859,"remaining_time":0.9446282577},
{"learn":[0.02243317716],"iteration":50,"passed_time":0.3210255521,"remaining_time":0.9378981817},
{"learn":[0.02233373359],"iteration":51,"passed_time":0.327408992,"remaining_time":0.9318563618},
{"learn":[0.02221376106],"iteration":52,"passed_time":0.3336741859,"remaining_time":0.9254736854},
{"learn":[0.02212670499],"iteration":53,"passed_time":0.3395522623,"remaining_time":0.9180487092},
{"learn":[0.02206888403],"iteration":54,"passed_time":0.3458764995,"remaining_time":0.9118562261},
{"learn":[0.02188374723],"iteration":55,"passed_time":0.3520505952,"remaining_time":0.9052729591},
{"learn":[0.02180926926],"iteration":56,"passed_time":0.3589917038,"remaining_time":0.9006283095},
{"learn":[0.02167467985],"iteration":57,"passed_time":0.36509008,"remaining_time":0.8938412302},
{"learn":[0.02132436032],"iteration":58,"passed_time":0.371113253,"remaining_time":0.8868977741},
{"learn":[0.02117037839],"iteration":59,"passed_time":0.3771578321,"remaining_time":0.8800349415},
{"learn":[0.02082681484],"iteration":60,"passed_time":0.3830560043,"remaining_time":0.8728653212},
{"learn":[0.02068598532],"iteration":61,"passed_time":0.3894270959,"remaining_time":0.8667893424},
{"learn":[0.02061052928],"iteration":62,"passed_time":0.3956630958,"remaining_time":0.8604102241},
{"learn":[0.02047246721],"iteration":63,"passed_time":0.4017428823,"remaining_time":0.8537036249},
{"learn":[0.02043579993],"iteration":64,"passed_time":0.4081715518,"remaining_time":0.8477409153},
{"learn":[0.02029433008],"iteration":65,"passed_time":0.4145757107,"remaining_time":0.8417143218},
{"learn":[0.02020649033],"iteration":66,"passed_time":0.4204992055,"remaining_time":0.8347223035},
{"learn":[0.02014417104],"iteration":67,"passed_time":0.4265546427,"remaining_time":0.8280178358},
{"learn":[0.01995188752],"iteration":68,"passed_time":0.4324882797,"remaining_time":0.8211009369},
{"learn":[0.01969033145],"iteration":69,"passed_time":0.4388122461,"remaining_time":0.8149370285},
{"learn":[0.01965402291],"iteration":70,"passed_time":0.4455575034,"remaining_time":0.8095340555},
{"learn":[0.01959088974],"iteration":71,"passed_time":0.4517333733,"remaining_time":0.8030815526},
{"learn":[0.01934506223],"iteration":72,"passed_time":0.4577997375,"remaining_time":0.7964461186},
{"learn":[0.0191273934],"iteration":73,"passed_time":0.4638119017,"remaining_time":0.7897337785},
{"learn":[0.01905562019],"iteration":74,"passed_time":0.4702830713,"remaining_time":0.7838051188},
{"learn":[0.01883636503],"iteration":75,"passed_time":0.4764970763,"remaining_time":0.7774425982},
{"learn":[0.01878684936],"iteration":76,"passed_time":0.482487621,"remaining_time":0.770726979},
{"learn":[0.01873873026],"iteration":77,"passed_time":0.4882763247,"remaining_time":0.7637142515},
{"learn":[0.01865947216],"iteration":78,"passed_time":0.4939078037,"remaining_time":0.7564916994},
{"learn":[0.01844041734],"iteration":79,"passed_time":0.4999838583,"remaining_time":0.7499757875},
{"learn":[0.01838829257],"iteration":80,"passed_time":0.50553979,"remaining_time":0.742706605},
{"learn":[0.01834010803],"iteration":81,"passed_time":0.5113097223,"remaining_time":0.7357871613},
{"learn":[0.0182383473],"iteration":82,"passed_time":0.5172108353,"remaining_time":0.7290803341},
{"learn":[0.0181699965],"iteration":83,"passed_time":0.5234281412,"remaining_time":0.7228293379},
{"learn":[0.01812555947],"iteration":84,"passed_time":0.5296072332,"remaining_time":0.7165274332},
{"learn":[0.01793569794],"iteration":85,"passed_time":0.5358007926,"remaining_time":0.7102475623},
{"learn":[0.01784889823],"iteration":86,"passed_time":0.5426897504,"remaining_time":0.7048728943},
{"learn":[0.01778926718],"iteration":87,"passed_time":0.5493494749,"remaining_time":0.699172059},
{"learn":[0.0175046777],"iteration":88,"passed_time":0.5559659603,"remaining_time":0.6933957483},
{"learn":[0.0174685668],"iteration":89,"passed_time":0.5625919042,"remaining_time":0.6876123273},
{"learn":[0.01741958338],"iteration":90,"passed_time":0.5690618585,"remaining_time":0.6816235448},
{"learn":[0.01736600882],"iteration":91,"passed_time":0.5754944619,"remaining_time":0.6755804552},
{"learn":[0.01725367965],"iteration":92,"passed_time":0.5817955737,"remaining_time":0.6693777031},
{"learn":[0.0169452331],"iteration":93,"passed_time":0.5882092334,"remaining_time":0.6632997739},
{"learn":[0.01688531443],"iteration":94,"passed_time":0.5948468518,"remaining_time":0.6574623099},
{"learn":[0.01662776789],"iteration":95,"passed_time":0.601748704,"remaining_time":0.6518944294},
{"learn":[0.0165316351],"iteration":96,"passed_time":0.6090060051,"remaining_time":0.6466764797},
{"learn":[0.01644512508],"iteration":97,"passed_time":0.6154896543,"remaining_time":0.640611681},
{"learn":[0.01637731384],"iteration":98,"passed_time":0.6219202599,"remaining_time":0.6344843055},
{"learn":[0.01616843213],"iteration":99,"passed_time":0.6284664137,"remaining_time":0.6284664137},
{"learn":[0.01604293015],"iteration":100,"passed_time":0.6347106402,"remaining_time":0.6221421127},
{"learn":[0.01600981446],"iteration":101,"passed_time":0.6411784476,"remaining_time":0.6160341947},
{"learn":[0.01598226642],"iteration":102,"passed_time":0.6477827506,"remaining_time":0.6100478331},
{"learn":[0.01592031858],"iteration":103,"passed_time":0.6540412137,"remaining_time":0.6037303511},
{"learn":[0.01579236765],"iteration":104,"passed_time":0.660281456,"remaining_time":0.5973975078},
{"learn":[0.01575686147],"iteration":105,"passed_time":0.6664625144,"remaining_time":0.5910139279},
{"learn":[0.01569288381],"iteration":106,"passed_time":0.6729504464,"remaining_time":0.5849008553},
{"learn":[0.01565744827],"iteration":107,"passed_time":0.6793393955,"remaining_time":0.5786965221},
{"learn":[0.01552829661],"iteration":108,"passed_time":0.6861709752,"remaining_time":0.5728583371},
{"learn":[0.01549040235],"iteration":109,"passed_time":0.6923769841,"remaining_time":0.5664902597},
{"learn":[0.01535216149],"iteration":110,"passed_time":0.6987680815,"remaining_time":0.5602735068},
{"learn":[0.01528300567],"iteration":111,"passed_time":0.7051485729,"remaining_time":0.5540453073},
{"learn":[0.01522493377],"iteration":112,"passed_time":0.7118231777,"remaining_time":0.5480408536},
{"learn":[0.01517438581],"iteration":113,"passed_time":0.7186221478,"remaining_time":0.5421184623},
{"learn":[0.01505982657],"iteration":114,"passed_time":0.7252821444,"remaining_time":0.5360781067},
{"learn":[0.0149772681],"iteration":115,"passed_time":0.7321291546,"remaining_time":0.5301624912},
{"learn":[0.01481066129],"iteration":116,"passed_time":0.7388698454,"remaining_time":0.5241555314},
{"learn":[0.01477670017],"iteration":117,"passed_time":0.7456794005,"remaining_time":0.5181839902},
{"learn":[0.014727045],"iteration":118,"passed_time":0.7520106823,"remaining_time":0.5118728174},
{"learn":[0.01461876427],"iteration":119,"passed_time":0.7581872457,"remaining_time":0.5054581638},
{"learn":[0.01458972796],"iteration":120,"passed_time":0.764090082,"remaining_time":0.4988687312},
{"learn":[0.01442927126],"iteration":121,"passed_time":0.7700498972,"remaining_time":0.4923269835},
{"learn":[0.01437910509],"iteration":122,"passed_time":0.7761112324,"remaining_time":0.4858582512},
{"learn":[0.01428968392],"iteration":123,"passed_time":0.781981714,"remaining_time":0.479279115},
{"learn":[0.01426180397],"iteration":124,"passed_time":0.7882381392,"remaining_time":0.4729428835},
{"learn":[0.01407304161],"iteration":125,"passed_time":0.7942222537,"remaining_time":0.4664479903},
{"learn":[0.01391004753],"iteration":126,"passed_time":0.8002714846,"remaining_time":0.4599985699},
{"learn":[0.01388095484],"iteration":127,"passed_time":0.8068727053,"remaining_time":0.4538658967},
{"learn":[0.01382016783],"iteration":128,"passed_time":0.8131998104,"remaining_time":0.4475750894},
{"learn":[0.01378483642],"iteration":129,"passed_time":0.8190664393,"remaining_time":0.441035775},
{"learn":[0.01374655505],"iteration":130,"passed_time":0.8248561162,"remaining_time":0.4344661986},
{"learn":[0.0135894359],"iteration":131,"passed_time":0.83052228,"remaining_time":0.4278448109},
{"learn":[0.01347785086],"iteration":132,"passed_time":0.8369332516,"remaining_time":0.4216129914},
{"learn":[0.01341565872],"iteration":133,"passed_time":0.8429811939,"remaining_time":0.4151996925},
{"learn":[0.01326332139],"iteration":134,"passed_time":0.8492941645,"remaining_time":0.4089194126},
{"learn":[0.01324120885],"iteration":135,"passed_time":0.8555641024,"remaining_time":0.4026184011},
{"learn":[0.01320581965],"iteration":136,"passed_time":0.8619085659,"remaining_time":0.3963521142},
{"learn":[0.01309278269],"iteration":137,"passed_time":0.8684149809,"remaining_time":0.3901574552},
{"learn":[0.01305413776],"iteration":138,"passed_time":0.8749675646,"remaining_time":0.3839785715},
{"learn":[0.01303401553],"iteration":139,"passed_time":0.8812820408,"remaining_time":0.3776923032},
{"learn":[0.01287999536],"iteration":140,"passed_time":0.8874533263,"remaining_time":0.3713457181},
{"learn":[0.0127080813],"iteration":141,"passed_time":0.8933511386,"remaining_time":0.3648899017},
{"learn":[0.01263301145],"iteration":142,"passed_time":0.8993157586,"remaining_time":0.3584685192},
{"learn":[0.01252731388],"iteration":143,"passed_time":0.9048907812,"remaining_time":0.3519019705},
{"learn":[0.01244993845],"iteration":144,"passed_time":0.9107505288,"remaining_time":0.3454570971},
{"learn":[0.01244067735],"iteration":145,"passed_time":0.9166503668,"remaining_time":0.3390350672},
{"learn":[0.01237072727],"iteration":146,"passed_time":0.9225072121,"remaining_time":0.3326046411},
{"learn":[0.01220971252],"iteration":147,"passed_time":0.9282914513,"remaining_time":0.3261564558},
{"learn":[0.01218744484],"iteration":148,"passed_time":0.9340737741,"remaining_time":0.3197165267},
{"learn":[0.01216777996],"iteration":149,"passed_time":0.9402310246,"remaining_time":0.3134103415},
{"learn":[0.01203944838],"iteration":150,"passed_time":0.9462026975,"remaining_time":0.3070459085},
{"learn":[0.01203113851],"iteration":151,"passed_time":0.9522484629,"remaining_time":0.3007100409},
{"learn":[0.01199745515],"iteration":152,"passed_time":0.958632828,"remaining_time":0.2944819798},
{"learn":[0.01196913799],"iteration":153,"passed_time":0.9644633085,"remaining_time":0.2880864428},
{"learn":[0.01189397523],"iteration":154,"passed_time":0.9706255143,"remaining_time":0.2817945042},
{"learn":[0.01183635319],"iteration":155,"passed_time":0.9768096729,"remaining_time":0.2755104206},
{"learn":[0.01181543821],"iteration":156,"passed_time":0.9828555199,"remaining_time":0.2691897284},
{"learn":[0.01179035136],"iteration":157,"passed_time":0.989084509,"remaining_time":0.2629211986},
{"learn":[0.01176660834],"iteration":158,"passed_time":0.9954492903,"remaining_time":0.2566881818},
{"learn":[0.01173515305],"iteration":159,"passed_time":1.001995058,"remaining_time":0.2504987645},
{"learn":[0.01170221866],"iteration":160,"passed_time":1.007947708,"remaining_time":0.2441612461},
{"learn":[0.01168007422],"iteration":161,"passed_time":1.013642455,"remaining_time":0.2377679832},
{"learn":[0.01166090835],"iteration":162,"passed_time":1.019840855,"remaining_time":0.2314976173},
{"learn":[0.01163014439],"iteration":163,"passed_time":1.025580036,"remaining_time":0.2251273251},
{"learn":[0.01155522067],"iteration":164,"passed_time":1.031784545,"remaining_time":0.2188633884},
{"learn":[0.01152927727],"iteration":165,"passed_time":1.038212011,"remaining_time":0.2126458335},
{"learn":[0.01151453758],"iteration":166,"passed_time":1.044478194,"remaining_time":0.2063938946},
{"learn":[0.01145154234],"iteration":167,"passed_time":1.050661142,"remaining_time":0.2001259319},
{"learn":[0.01144228085],"iteration":168,"passed_time":1.05690563,"remaining_time":0.1938702635},
{"learn":[0.01135038171],"iteration":169,"passed_time":1.06358081,"remaining_time":0.1876907312},
{"learn":[0.01124866019],"iteration":170,"passed_time":1.069776225,"remaining_time":0.1814240382},
{"learn":[0.01114018079],"iteration":171,"passed_time":1.075872041,"remaining_time":0.1751419602},
{"learn":[0.01103962847],"iteration":172,"passed_time":1.08204251,"remaining_time":0.1688736865},
{"learn":[0.01102601979],"iteration":173,"passed_time":1.087912505,"remaining_time":0.1625616387},
{"learn":[0.01100807037],"iteration":174,"passed_time":1.094374492,"remaining_time":0.1563392131},
{"learn":[0.01096765102],"iteration":175,"passed_time":1.100581355,"remaining_time":0.1500792756},
{"learn":[0.01083838594],"iteration":176,"passed_time":1.106616547,"remaining_time":0.1437976304},
{"learn":[0.0108006929],"iteration":177,"passed_time":1.112583946,"remaining_time":0.1375103753},
{"learn":[0.01078171172],"iteration":178,"passed_time":1.118268216,"remaining_time":0.1311934779},
{"learn":[0.01074479875],"iteration":179,"passed_time":1.124652652,"remaining_time":0.1249614058},
{"learn":[0.01073001737],"iteration":180,"passed_time":1.130417608,"remaining_time":0.1186626218},
{"learn":[0.01061259985],"iteration":181,"passed_time":1.136833395,"remaining_time":0.112434072},
{"learn":[0.01057623528],"iteration":182,"passed_time":1.143031146,"remaining_time":0.1061832212},
{"learn":[0.01057102882],"iteration":183,"passed_time":1.148823492,"remaining_time":0.09989769498},
{"learn":[0.01055233263],"iteration":184,"passed_time":1.15512301,"remaining_time":0.09365862244},
{"learn":[0.01053532776],"iteration":185,"passed_time":1.161624458,"remaining_time":0.08743409896},
{"learn":[0.01051082647],"iteration":186,"passed_time":1.167989507,"remaining_time":0.0811971315},
{"learn":[0.01048959113],"iteration":187,"passed_time":1.173875952,"remaining_time":0.07492825225},
{"learn":[0.01045817529],"iteration":188,"passed_time":1.179769939,"remaining_time":0.0686638589},
{"learn":[0.01043821713],"iteration":189,"passed_time":1.185794717,"remaining_time":0.06241024826},
{"learn":[0.01042074883],"iteration":190,"passed_time":1.191381479,"remaining_time":0.05613839428},
{"learn":[0.01037973078],"iteration":191,"passed_time":1.197354977,"remaining_time":0.04988979072},
{"learn":[0.01028844562],"iteration":192,"passed_time":1.203435799,"remaining_time":0.04364793053},
{"learn":[0.01026360221],"iteration":193,"passed_time":1.209392632,"remaining_time":0.03740389583},
{"learn":[0.01024456293],"iteration":194,"passed_time":1.215619049,"remaining_time":0.0311697192},
{"learn":[0.01021899297],"iteration":195,"passed_time":1.221578643,"remaining_time":0.0249301764},
{"learn":[0.01020236323],"iteration":196,"passed_time":1.22804917,"remaining_time":0.01870125639},
{"learn":[0.01018644124],"iteration":197,"passed_time":1.234363474,"remaining_time":0.01246831792},
{"learn":[0.01016346054],"iteration":198,"passed_time":1.240464289,"remaining_time":0.006233488888},
{"learn":[0.0101213953],"iteration":199,"passed_time":1.246448402,"remaining_time":0}
]}